pyevals/BuildClassification.py
pyevals/BuildRegression.py
pyevals/Plots.py
pyevals/RegressionMetrics.py
pyevals/__init__.py
pyevals/exceptions.py
pyevals/utils.py
pyevals-1.3.8.dist-info/LICENSE
pyevals-1.3.8.dist-info/METADATA
pyevals-1.3.8.dist-info/WHEEL
pyevals-1.3.8.dist-info/top_level.txt
pyevals-1.3.8.dist-info/RECORD
