Metadata-Version: 2.1
Name: pyevals
Version: 1.3.8
Summary: A simple Python Package for Model Evalutaion
Home-page: UNKNOWN
Author: Gokul and Anand
Author-email: adsp.tsgkr@gmail.com
License: UNKNOWN
Platform: UNKNOWN
Classifier: Programming Language :: Python :: 3
Classifier: License :: OSI Approved :: MIT License
Classifier: Operating System :: OS Independent
Requires-Dist: sklearn
Requires-Dist: numpy
Requires-Dist: pandas
Requires-Dist: PyPDF2
Requires-Dist: seaborn
Requires-Dist: matplotlib
Requires-Dist: scikit-learn (==0.24.1)
